neurondb/__init__.py
neurondb/database.py
neurondb/core/__init__.py
neurondb/core/neuron.py
neurondb/core/synapse.py
neurondb-0.1.0.dist-info/METADATA
neurondb-0.1.0.dist-info/WHEEL
neurondb-0.1.0.dist-info/top_level.txt
neurondb-0.1.0.dist-info/RECORD
