Metadata-Version: 2.4
Name: neurondb
Version: 0.1.0
Summary: A brain-inspired, property-graph database in Python.
Author: Your Name
Requires-Python: >=3.7
Dynamic: author
Dynamic: requires-python
Dynamic: summary
